cropmetapop/CropMetaPop.py
cropmetapop/Fitness.py
cropmetapop/FreqAll.py
cropmetapop/GenotypeLocus.py
cropmetapop/GenotypeMultiLocus.py
cropmetapop/Locus.py
cropmetapop/MetaPop.py
cropmetapop/Population.py
cropmetapop/ProgressBar.py
cropmetapop/Reader.py
cropmetapop/Result.py
cropmetapop/ResultExchange.py
cropmetapop/ResultGenoMono.py
cropmetapop/ResultGenoMulti.py
cropmetapop/ResultHaplotype.py
cropmetapop/Simu.py
cropmetapop/Writer.py
cropmetapop/__init__.py
cropmetapop-1.1.2.data/scripts/cropmetapop
cropmetapop-1.1.2.dist-info/METADATA
cropmetapop-1.1.2.dist-info/WHEEL
cropmetapop-1.1.2.dist-info/top_level.txt
cropmetapop-1.1.2.dist-info/RECORD
